coalispr/__init__.py
coalispr/__main__.py
coalispr/coalispr.py
coalispr/LICENCES/EUPL v1_2 NL.txt
coalispr/LICENCES/EUPL-1.2 EN.txt
coalispr/LICENCES/Logo_EUPL.svg
coalispr/bedgraph_analyze/__init__.py
coalispr/bedgraph_analyze/bam_counters.py
coalispr/bedgraph_analyze/bedgraph_plots.py
coalispr/bedgraph_analyze/collect_bedgraphs.py
coalispr/bedgraph_analyze/compare.py
coalispr/bedgraph_analyze/experiment.py
coalispr/bedgraph_analyze/genom.py
coalispr/bedgraph_analyze/info_plots.py
coalispr/bedgraph_analyze/process_bamdata.py
coalispr/bedgraph_analyze/process_bedgraphs.py
coalispr/bedgraph_analyze/references.py
coalispr/bedgraph_analyze/store.py
coalispr/bedgraph_analyze/unselected.py
coalispr/count_analyze/__init__.py
coalispr/count_analyze/annot.py
coalispr/count_analyze/countfile_plots.py
coalispr/count_analyze/filter_data.py
coalispr/count_analyze/groupcompare_plots.py
coalispr/count_analyze/load_countfile.py
coalispr/count_analyze/panel_plotters.py
coalispr/count_analyze/regioncount_plots.py
coalispr/resources/__init__.py
coalispr/resources/clearup-Xtra_gtf.txt
coalispr/resources/cmd_parser.py
coalispr/resources/constant.py
coalispr/resources/dialog.py
coalispr/resources/experiment_table.tsv
coalispr/resources/numeric.py
coalispr/resources/plot_utilities.py
coalispr/resources/utilities.py
coalispr/resources/constant_in/1_heading.txt
coalispr/resources/constant_in/2_shared.txt
coalispr/resources/constant_in/3_EXP.txt
coalispr/resources/constant_in/3_h99t.txt
coalispr/resources/constant_in/__init__.py
coalispr/resources/constant_in/make_constant.py
coalispr/resources/constant_out/__init__.py
coalispr/resources/constant_out/constant_RESET.py
coalispr/resources/constant_out/constant_h99.py
coalispr/resources/constant_out/constant_h99t.py
coalispr/resources/constant_out/constant_jec21.py
coalispr/resources/constant_out/constant_mouse.py
coalispr/resources/constant_out/constant_mouse45s.py
coalispr/resources/share/__init__.py
coalispr/resources/share/clean_fasta.py
coalispr-0.7.8.dist-info/LICENCE.txt
coalispr-0.7.8.dist-info/METADATA
coalispr-0.7.8.dist-info/WHEEL
coalispr-0.7.8.dist-info/entry_points.txt
coalispr-0.7.8.dist-info/top_level.txt
coalispr-0.7.8.dist-info/RECORD
