Metadata-Version: 2.1
Name: coalispr
Version: 0.7.8
Summary: Small RNA-Seq analysis starting from bedgraph files
Author-email: Rob van Nues <coalispr@disroot.org>
Maintainer-email: Rob van Nues <coalispr@disroot.org>
License: EUROPEAN UNION PUBLIC LICENCE v. 1.2 or later
Project-URL: Homepage, https://codeberg.org/coalispr/coalispr
Project-URL: Documentation, https://coalispr.codeberg.page/
Keywords: matplotlib,pandas,pysam,pyCRAC,bedgraph,RNA,bam
Classifier: Development Status :: 4 - Beta
Classifier: Environment :: Console
Classifier: Intended Audience :: Education
Classifier: Intended Audience :: Developers
Classifier: Intended Audience :: Science/Research
Classifier: Operating System :: POSIX
Classifier: Programming Language :: Python :: 3.11
Classifier: Topic :: Scientific/Engineering :: Bio-Informatics
Requires-Python: >=3.11
License-File: LICENCE.txt
Requires-Dist: numpy >=1.26
Requires-Dist: pandas >=1.5
Requires-Dist: matplotlib >=3.8
Requires-Dist: seaborn >=0.13
Requires-Dist: pysam >=0.20
Requires-Dist: PyQt6
Provides-Extra: docs
Requires-Dist: sphinx ; extra == 'docs'
Requires-Dist: furo ; extra == 'docs'
Requires-Dist: sphinx-autoapi ; extra == 'docs'
Requires-Dist: rich ; extra == 'docs'
Requires-Dist: common-mark ; extra == 'docs'
